# String

String实现了CharSequence、Comparable，并且是一个最终类

String对象是不可变的。String类中每一个看起来会修改String值的方法，实际上都是创建了一个全新的String对象，以包含修改后的字符串内容。而最初的String对象不会改动

String底层是字符数组，内部维护了以下字段：

~~~java
private final char value[];
~~~

这个字段在创建String对象时由构造器初始化，之后的所有声明周期中value数组都不会改变

String提供多个重载构造器以适应不同情况：

~~~java
public String();
public String(String original);
public String(char value[]);
public String(char value[], int offset, int count);
public String(int[] codePoints, int offset, int count);
public String(byte ascii[], int hibyte, int offset, int count);
public String(StringBuffer buffer);
public String(StringBuilder builder);
~~~

## 常用方法

下面汇总String的常用操作，重载方法合并为一行：

| 方法名                        | 说明                                                         |
| ----------------------------- | ------------------------------------------------------------ |
| `length()`                    | String中字符的个数                                           |
| `chaAt()`                     | 取得String中改索引位置上的char                               |
| `getChars(),getBytes()`       | 赋值char或byte到一个目标数组中                               |
| `toCharArray()`               | 生成一个`char[]`，包含String的所有字符                       |
| `equals(),equalsIgnoreCase()` | 比较两个String的内容是否相同                                 |
| `compareTo()`                 | 按照字典顺序比较String的内容                                 |
| `contains()`                  | 如果该String对象包含参数的内容，则返回true                   |
| `contentEquals()`             | 如果该String与参数的内容完全一致，则返回true                 |
| `equalsIgnoreCase()`          | 忽略大小写，比较两个String是否相同                           |
| `regionMatches()`             | 测试两个字符串区域是否相等                                   |
| `startsWith()`                | 判断该String是否以指定的参数字符串起始                       |
| `endsWith()`                  | 判断该String是否以指定的参数字符串结尾                       |
| `indexOf(),lastIndexOf()`     | 返回指定参数字符在该String中第一次/最后一次出现的索引，如果String不包含次参数，返回-1 |
| `subString()(subSequence())`  | 返回一个新的String，以包含参数指定的子字符串                 |
| `concat()`                    | 返回一个新的String对象，内容以原始String连接上参数String     |
| `replace()`                   | 返回替换字符后的String对象，如果没有改变发生，返回原String对象 |
| `toLowerCase(),toUpperCase()` | 将字符的大小写改变后，返回一个新的String对象，如果没有改变发生，返回原String对象 |
| `trim()`                      | 将String两端的空白字符删除后，返回一个新的String 对象，如果没有改变发生，返回原String对象 |
| `valueOf()`                   | 返回一个表示参数内容的String                                 |
| `intern()`                    | 为每个唯一的字符序列生成一个且仅生成一个String引用           |

## String与正则表达式

正则表达式时一种强大灵活的文本处理工具，通过正则可以对字符串进行搜索匹配，以对字符串进行更复杂，更精确的操作

正则表达式的具体语法这里不做展开；只讲几个与String提供的与正则相关的方法：

| 方法                                                     | 说明                                                        |
| -------------------------------------------------------- | ----------------------------------------------------------- |
| `boolean matches(String regex)`                          | 判断此字符串是否与给定的正则表达式匹配                      |
| `String replaceAll(String regex, String replacement)`    | 用给定的replacement替换所有与给定正则表达式匹配的子字符串。 |
| `String replaceFirst(String regex, String replacement) ` | 用给定的replacement替换第一个与给定正则表达式匹配的子字符串 |
| `String[] split(String regex, int limit)`                | 以给定正则表达式的匹配的子字符串为分隔符，拆分此字符串。    |

这些方法底层主要通过`Partten`类来实现

## 字符串常量池

注意到String有一个本地方法：

~~~java
public native String intern();
~~~

String类维护一个字符串常量池。当调用intern方法时，如果池中已经包含一个由equals(object)方法确定的与此string对象相等的字符串，则返回池中的字符串。否则，将此String对象添加到池中，并返回对该String对象的引用。

所以对于两个相等的字符串，它们调用`intern()`方法返回的String对象的地址是相等的，如：

~~~java
String a = new String("1");
String b = new String("1");
System.out.println(a == b); //false
System.out.println(a.intern() == b.intern()); //true
~~~

并且所有字面值字符串和字符串值常量表达式都被internned。即它们在使用时已经被维护在字符串常量池中了：

~~~java
System.out.println("1" == "1"); // true
~~~

## 重载操作符`+`

重载指一个操作符在应用于不同的类时，有不同的行为

Java中只有`+`和`+=`操作符有重载行为。Java并不允许程序员自己定义重载行为

二元运算符`+`和`+=`的两个作用对象都为Number时，会进行算数运算操作，返回一个Number；

作用对象中有String时，会进行字符串拼接操作，返回一个String。

### `+`重载的原理

如果`+`作用于两个字符串字面量，JVM会直接将其当作一个字符串：

~~~java
public static void main(String[] args) {
    String s = "1" +"2";
}
~~~

它对应的字节码指令为：

~~~java
public static void main(java.lang.String[]);
Code:
   0: ldc           #2                  // String 12
   2: astore_1
   3: return
~~~

可见：JVM直接将`"1" +"2"`看作常量`"12"`加载到操作数栈

但是如果`+`的作用对象中有引用变量，那么情况将不同：

~~~java
public static void main(String[] args) {
    String a = "1" + String.class;
}
~~~

其对应的字节码指令为：

~~~java
public static void main(java.lang.String[]);
    Code:
       0: new           #2                  // class java/lang/StringBuilder
       3: dup
       4: invokespecial #3                  // Method java/lang/StringBuilder."<init>":()V
       7: ldc           #4                  // String 1
       9: invokevirtual #5                  // Method java/lang/StringBuilder.append:(Ljava/lang/String;)Ljava/lang/StringBuilder;
      12: ldc           #6                  // class java/lang/String
      14: invokevirtual #7                  // Method java/lang/StringBuilder.append:(Ljava/lang/Object;)Ljava/lang/StringBuilder;
      17: invokevirtual #8                  // Method java/lang/StringBuilder.toString:()Ljava/lang/String;
      20: astore_1
      21: return
~~~

可以看到JVM实际上会创建一个`StringBuilder`，然后调用其`append`方法进行字符串拼接，最终调用其`toString`方法返回最终结果

`StringBuilder`维护一个字符串缓冲区，能进行高效的字符串增删拼接操作

# StringBuilder

因为String不可变的特性，每次对String的增删改操作都将产生新的String对象；这样效率低下并浪费内存

为了高效处理对字符串的频繁操作，Java提供了StringBuilder

StringBuilder内部维护以下字段：

~~~java
char[] value;
~~~

所有的字符串拼接，删除操作实际上是直接操作的value字符数组，这样，在频繁操作字符串时，不会像String一样产生许多无用的中间对象；

和ArrayList一样，定长数组value在执行append操作时会进行判断是否扩容，以保证value的容量足够

在StringBuilder初始化时，如果不指定容量并且没有初始字符串，那么value长度默认为16

## StringBuilder方法

StringBuilder主要提供增删插入操作：

| 方法名          | 重载参数                                                     | 说明                                                         |
| --------------- | ------------------------------------------------------------ | ------------------------------------------------------------ |
| `append()`      | `Object`、`String`、基本数据类型、`StringBuilder`、`char[]`  | 将传入的参数的字符串形式附加到内部维护的char数组最后         |
| `delete()`      | index索引、start到end范围                                    | 删除此序列指定位置/范围中的字符                              |
| `insert()`      | `char[]`、`CharSequence`、`Object`、`String`、基本数据类型offset：插入的偏移位置 | 在指定偏移位置插入指定入参的字符串形式、原来的字符依次向后移 |
| `indexOf()`     | `String`                                                     | 返回指定子字符串第一次出现的索引                             |
| `lastIndexOf()` | `String`                                                     | 返回指定子字符串最后次出现的索引                             |
| `reverse()`     |                                                              | 反转字符串                                                   |
| `toString()`    |                                                              | 返回value字符数组对应的String                                |

注意到除了`toString`、`lastIndexOf`、`indexOf`方法，其他展示的方法最后都返回自己的引用，如：

~~~java
public StringBuilder insert(int offset, float f) {
    super.insert(offset, f);
    return this;
}
~~~

这样在使用`StringBuilder`编程时，可以连续调用它的方法，如：

~~~java
StringBuilder sb = new StringBuilder();
String s = sb.append("123").append(4).reverse().toString();
System.out.println(s);
~~~

## StringBuffer和StringBuilder

StringBuffer和StringBuilder提供的api几乎一样，它们主要的不同在StringBuffer时线程安全的，StringBuffer的所有操作方法都使用`synchronized`关键字修饰，是同步的，在多线程环境下是线程安全的。

在可能的情况下，建议优先使用StringBuilder而不是StringBuffer，因为在大多数实现下StringBuilder会更快。

